autogonai/__init__.py
autogonai/connector.py
autogonai/constants.py
autogonai/errors.py
autogonai/core/__init__.py
autogonai/core/api.py
autogonai/core/qore.py
autogonai/development/__init__.py
autogonai/development/auto_deep_learning.py
autogonai/development/auto_machine_learning.py
autogonai/development/base.py
autogonai/development/data_processing.py
autogonai/development/deep_learning.py
autogonai/development/machine_learning.py
examples/__init__.py
examples/pipleine_test.py
examples/project_test.py
autogonai_python-0.1.9.dist-info/LICENSE
autogonai_python-0.1.9.dist-info/METADATA
autogonai_python-0.1.9.dist-info/WHEEL
autogonai_python-0.1.9.dist-info/top_level.txt
autogonai_python-0.1.9.dist-info/RECORD
