Metadata-Version: 2.1
Name: autogonai-python
Version: 0.1.9
Summary: Python connector for Autogon Public APIs
Home-page: https://github.com/autogoninc/autogonai-python
Author: Autogon AI Inc.
Author-email: infrastructure@autogon.ai
Maintainer: David Mbatuegwu, Aaron Nwokoro
Maintainer-email: infrastructure@autogon.ai
License: UNKNOWN
Platform: UNKNOWN
Classifier: Development Status :: 4 - Beta
Classifier: Intended Audience :: Developers
Classifier: License :: OSI Approved :: MIT License
Classifier: Programming Language :: Python :: 3
Classifier: Programming Language :: Python :: 3.6
Classifier: Programming Language :: Python :: 3.7
Classifier: Programming Language :: Python :: 3.8
Classifier: Programming Language :: Python :: 3.9
Classifier: Programming Language :: Python :: 3.10
Requires-Python: >=3.6
License-File: LICENSE
Requires-Dist: python-dotenv ==1.0.0
